CHANGELOG.txt
MANIFEST.in
README.txt
downloadpy.py
license.txt
setup.py
downloadpy.egg-info/PKG-INFO
downloadpy.egg-info/SOURCES.txt
downloadpy.egg-info/dependency_links.txt
downloadpy.egg-info/requires.txt
downloadpy.egg-info/top_level.txt