Metadata-Version: 2.1
Name: downloadpy
Version: 0.0.1
Summary: Download Files from Internet
Home-page: 
Author: Linix Red
Author-email: linixred@gmail.com
License: MIT
Keywords: download
Classifier: Development Status :: 5 - Production/Stable
Classifier: Intended Audience :: Education
Classifier: Operating System :: Microsoft :: Windows :: Windows 11
Classifier: License :: OSI Approved :: MIT License
Classifier: Programming Language :: Python :: 3
License-File: license.txt
